cimlib/CIMlib.py
cimlib/__init__.py
splight_cim-1.0.2.dist-info/METADATA
splight_cim-1.0.2.dist-info/WHEEL
splight_cim-1.0.2.dist-info/top_level.txt
splight_cim-1.0.2.dist-info/RECORD
