Metadata-Version: 2.1
Name: splight-cim
Version: 1.0.2
Summary: Parse CIM RDF XML files and get output in JSON format
Home-page: https://bitbucket.org/splight-dev/test/src/master/
Author: Splight
Author-email: splight@splight-ae.com
License: MIT
Platform: UNKNOWN
Classifier: License :: OSI Approved :: MIT License
Classifier: Programming Language :: Python :: 3
Classifier: Programming Language :: Python :: 3.7
